uberon_py/__init__.py
uberon_py/obo.py
uberon_py-0.0a1.dist-info/LICENSE.md
uberon_py-0.0a1.dist-info/METADATA
uberon_py-0.0a1.dist-info/WHEEL
uberon_py-0.0a1.dist-info/top_level.txt
uberon_py-0.0a1.dist-info/RECORD
