Metadata-Version: 2.1
Name: uberon-py
Version: 0.0a1
Summary: `uberon_py` is a package for querying the Uberon ontology from python.
Home-page: https://github.com/NatalieThurlby/uberon-py
Author: Natlie Thurlby
Author-email: natalie.thurlby@bristol.ac.uk
License: GPLv3
Platform: UNKNOWN
